Workbook

Sheet Resumen
A1: Análisis de compras: equipos solares (compra por unidad, Argentina)
A2: Precios de referencia relevados en web el 11/10/2026. Muchos datos tienen semanas o meses: confirmá cada precio antes de presupuestar.
A4: Categoría | B4: Recomendación principal (precio/calidad) | C4: Alternativa | D4: Por qué
A5: Paneles | B5: Trina Solar Vertex 550 W (Enertik o su tienda en Mercado Libre) | C5: Solartex 580 W bifacial (TexSolar) / Znshine 580 W bifacial (ML) | D5: Marca Tier 1, se vende por unidad, stock habitual y garantía con distribuidor oficial.
A6: Inversor on-grid con inyección cero | B6: Deye on-grid 2 / 3 / 4 kW (trae limitación de inyección con sensor CT) | C6: Growatt MIN + limitador Growatt SPM / SolaX X1-Mini | D6: Deye resuelve la inyección cero sin comprar otro medidor. Ideal para el cliente sin baterías.
A7: Inversor híbrido | B7: Deye SUN-5K-SG04LP1 5 kW 48 V monofásico | C7: Growatt SPH / SPF (cotizar) | D7: Muy difundido en Argentina, buen soporte, compatible con baterías Deye, Dyness y Pylontech.
A8: Baterías litio 48 V | B8: Deye SE-F5 5,12 kWh (Enertik) | C8: Dyness DL5.0C 5,12 kWh (ML) / Pylontech US5000 (premium) | D8: El mejor $/kWh relevado. Con inversor Deye, la comunicación BMS es directa.
A9: Limitador / medidor | B9: Si usás Deye: el CT que trae el inversor | C9: Growatt SPM monofásico / TPM trifásico | D9: Solo hace falta si el inversor no trae limitación integrada.
A10: Cable solar y MC4 | B10: Rollo de cable solar 6 mm² rojo y negro (IEC 62930 / TÜV) + MC4 de una sola marca | C10: Cable armado con MC4 (para tramos cortos) | D10: No mezcles MC4 de marcas distintas: es causa típica de puntos calientes.
A11: Protecciones CC | B11: Portafusibles gPV 1000 V + seccionador CC 1000 V + DPS CC tipo 2 (Suntree, Chint o similar) | C11: Tablero CC premontado | D11: Precios no encontrados online: cotizar (Hissuma materiales, Enertik, casas de electricidad).
A12: Protecciones CA | B12: Térmica, disyuntor diferencial y DPS CA de marca reconocida (Schneider, ABB, Siemens, Sica, Jeluz) | C12: — | D12: Se compran en cualquier casa de electricidad. Precio de mercado común.
A13: Estructura | B13: Proveedor local de estructura de aluminio coplanar para chapa o teja | C13: Perfilería y anclajes por tu cuenta | D13: No encontré precios argentinos online: cotizar con medidas de panel y tipo de techo.
A15: CÓMO USAR ESTE ARCHIVO
A16: 1) Hoja 'Productos': cuando cotices, cargá el precio nuevo en la columna amarilla 'Precio actualizado' y la fecha. La columna 'Precio a usar' toma ese valor automáticamente.
A17: 2) Hoja 'Kits': cambiá las cantidades (texto azul) y cargá los ítems 'a cotizar' (celdas amarillas). El total se recalcula solo.
A18: 3) Hoja 'Proveedores': dónde comprar y qué vende cada uno.
A20: CONSEJOS DE COMPRA
A21: • Compará siempre con IVA incluido. Algunas tiendas publican + IVA o 'sin impuestos nacionales' (está marcado en la columna IVA).
A22: • Los equipos se compran con el anticipo del cliente, nunca con tu plata.
A23: • Pedí factura A o B a tu nombre (monotributo) y guardá la garantía de cada equipo: la vas a necesitar para responderle al cliente.
A24: • Con 2 o 3 obras, pedí cuenta de instalador en Enertik y en algún mayorista (Hissuma, Enerton): los precios suelen bajar bastante.
A25: • Comprá inversor y batería compatibles entre sí (misma marca o en la lista de compatibilidad del fabricante).
A26: • Leyenda de colores: texto azul = dato que podés cambiar · celdas amarillas = completar · texto verde = trae datos de otra hoja.

Sheet Productos
A1: ID | B1: Categoría | C1: Producto / modelo | D1: Marca | E1: Capacidad | F1: Unidad | G1: Tienda | H1: Precio ref. (ARS) | I1: IVA | J1: Antigüedad del dato | K1: Precio actualizado (completar) | L1: Fecha cotización (completar) | M1: Precio a usar (ARS) | N1: $ por W o por kWh | O1: Link | P1: Comentario
A2: PAN-01 | B2: Panel | C2: Trina Vertex 550 W (TSM-550DE19) | D2: Trina Solar | E2: 550 | F2: W | G2: Enertik | H2: 224000 | I2: Incluido | J2: ~3 meses | M2: =IF(K2<>"",K2,IF(H2="","",H2)) -> 224000 | N2: =IF(AND(ISNUMBER(E2),ISNUMBER(M2),OR(F2="W",F2="kWh")),M2/E2,"") -> 407.27273 | O2: https://enertik.com/ar/tienda/ | P2: Pallet de 31 u.: $6.710.000 (≈ $216.452/u).
A3: PAN-02 | B3: Panel | C3: Trina Vertex 550 W | D3: Trina Solar | E3: 550 | F3: W | G3: Enertik shop | H3: 235900 | I3: Incluido | J3: Viejo (tipo de cambio 1028) | M3: =IF(K3<>"",K3,IF(H3="","",H3)) -> 235900 | N3: =IF(AND(ISNUMBER(E3),ISNUMBER(M3),OR(F3="W",F3="kWh")),M3/E3,"") -> 428.90909 | O3: https://shop.enertik.ar/shop/category/paneles-solares-247 | P3: Lista con TC desactualizado.
A4: PAN-03 | B4: Panel | C4: Trina Vertex 550 W | D4: Trina Solar | E4: 550 | F4: W | G4: Mercado Libre (por Enertik) | H4: 244065 | I4: Incluido | J4: Actual al relevar | M4: =IF(K4<>"",K4,IF(H4="","",H4)) -> 244065 | N4: =IF(AND(ISNUMBER(E4),ISNUMBER(M4),OR(F4="W",F4="kWh")),M4/E4,"") -> 443.75455 | O4: https://listado.mercadolibre.com.ar/panel-solar-550w | P4: Permite cuotas.
A5: PAN-04 | B5: Panel | C5: Solartex 580 W bifacial | D5: Solartex | E5: 580 | F5: W | G5: TexSolar (Rosario) | H5: =179900*1.21 -> 217679 | I5: +IVA (sumado 21%) | J5: Sin fecha | M5: =IF(K5<>"",K5,IF(H5="","",H5)) -> 217679 | N5: =IF(AND(ISNUMBER(E5),ISNUMBER(M5),OR(F5="W",F5="kWh")),M5/E5,"") -> 375.30862 | O5: https://texsolar.com.ar/panel-solar-580w/ | P5: Lista $179.900 + IVA. Envío desde Rosario.
A6: PAN-05 | B6: Panel | C6: Znshine 580 W bifacial | D6: Znshine | E6: 580 | F6: W | G6: Mercado Libre | H6: 220775 | I6: Incluido | J6: Actual al relevar | M6: =IF(K6<>"",K6,IF(H6="","",H6)) -> 220775 | N6: =IF(AND(ISNUMBER(E6),ISNUMBER(M6),OR(F6="W",F6="kWh")),M6/E6,"") -> 380.64655 | O6: https://articulo.mercadolibre.com.ar/MLA-1913420384-panel-solar-bifacial-monocristalino-580w-media-celda-perc-_JM | P6: Marca menos conocida en el país.
A7: PAN-06 | B7: Panel | C7: Amerisolar 580 W | D7: Amerisolar | E7: 580 | F7: W | G7: JF Solar | H7: 215579.01 | I7: Incluido | J7: ~19 meses (viejo) | M7: =IF(K7<>"",K7,IF(H7="","",H7)) -> 215579.01 | N7: =IF(AND(ISNUMBER(E7),ISNUMBER(M7),OR(F7="W",F7="kWh")),M7/E7,"") -> 371.68795 | O7: https://jfsolar.com.ar/paneles-solares/ | P7: Precio contado. Dato viejo.
A8: PAN-07 | B8: Panel | C8: JA Solar 610 W bifacial | D8: JA Solar | E8: 610 | F8: W | G8: JF Solar | H8: 267094.48 | I8: Incluido | J8: ~19 meses (viejo) | M8: =IF(K8<>"",K8,IF(H8="","",H8)) -> 267094.48 | N8: =IF(AND(ISNUMBER(E8),ISNUMBER(M8),OR(F8="W",F8="kWh")),M8/E8,"") -> 437.8598 | O8: https://jfsolar.com.ar/paneles-solares/ | P8: Precio contado. Dato viejo.
A9: INV-01 | B9: Inversor on-grid | C9: Deye 2 kW on-grid (WiFi + CT incluido) | D9: Deye | E9: 2000 | F9: W | G9: SuriaEnergy | H9: 726754 | I9: Verificar | J9: Sin fecha | M9: =IF(K9<>"",K9,IF(H9="","",H9)) -> 726754 | N9: =IF(AND(ISNUMBER(E9),ISNUMBER(M9),OR(F9="W",F9="kWh")),M9/E9,"") -> 363.377 | O9: https://shop.suriaenergy.com/40c760-Inversores%20On%20Grid | P9: Con limitación de inyección cero.
A10: INV-02 | B10: Inversor on-grid | C10: Deye 3 kW on-grid | D10: Deye | E10: 3000 | F10: W | G10: Mercado Libre | H10: 936889 | I10: Incluido | J10: Sin fecha | M10: =IF(K10<>"",K10,IF(H10="","",H10)) -> 936889 | N10: =IF(AND(ISNUMBER(E10),ISNUMBER(M10),OR(F10="W",F10="kWh")),M10/E10,"") -> 312.29633 | O10: https://listado.mercadolibre.com.ar/inversor-on-grid-3-kw | P10: Confirmá que incluya el CT.
A11: INV-03 | B11: Inversor on-grid | C11: Deye 4 kW on-grid | D11: Deye | E11: 4000 | F11: W | G11: SuriaEnergy | H11: 1128781 | I11: Verificar | J11: Sin fecha | M11: =IF(K11<>"",K11,IF(H11="","",H11)) -> 1128781 | N11: =IF(AND(ISNUMBER(E11),ISNUMBER(M11),OR(F11="W",F11="kWh")),M11/E11,"") -> 282.19525 | O11: https://shop.suriaenergy.com/40c760-Inversores%20On%20Grid
A12: INV-04 | B12: Inversor on-grid | C12: SolaX X1-Mini 2 kW | D12: SolaX | E12: 2000 | F12: W | G12: Ingeniería Boggio | H12: 650141.55 | I12: Sin impuestos nacionales | J12: Sin fecha | M12: =IF(K12<>"",K12,IF(H12="","",H12)) -> 650141.55 | N12: =IF(AND(ISNUMBER(E12),ISNUMBER(M12),OR(F12="W",F12="kWh")),M12/E12,"") -> 325.07078 | O12: https://www.ingenieriaboggio.com.ar/shop/category/energia-solar-inversores-on-grid-3205 | P12: Sumale impuestos para comparar.
A13: INV-05 | B13: Inversor híbrido | C13: Deye SUN-5K-SG04LP1 5 kW 48 V | D13: Deye | E13: 5000 | F13: W | G13: Mercado Libre | H13: 3916000 | I13: Incluido | J13: Actual al relevar | M13: =IF(K13<>"",K13,IF(H13="","",H13)) -> 3916000 | N13: =IF(AND(ISNUMBER(E13),ISNUMBER(M13),OR(F13="W",F13="kWh")),M13/E13,"") -> 783.2 | O13: https://articulo.mercadolibre.com.ar/MLA-1142269496-inversor-hibrido-monofasico-5kw-deye-48v-220v-solar-_JM | P13: Precio para CABA y GBA. Otros vendedores: $4,2 a $6,5 M.
A14: LIM-01 | B14: Limitador | C14: Growatt SPM monofásico | D14: Growatt | F14: u | G14: SuriaEnergy | H14: 231946 | I14: Verificar | J14: Sin fecha | M14: =IF(K14<>"",K14,IF(H14="","",H14)) -> 231946 | N14: =IF(AND(ISNUMBER(E14),ISNUMBER(M14),OR(F14="W",F14="kWh")),M14/E14,"") | O14: https://shop.suriaenergy.com/40c760-Inversores%20On%20Grid | P14: Solo para inversores Growatt.
A15: LIM-02 | B15: Limitador | C15: Growatt SPM monofásico | D15: Growatt | F15: u | G15: Electroimpulso | H15: 329999 | I15: Verificar | J15: Sin fecha | M15: =IF(K15<>"",K15,IF(H15="","",H15)) -> 329999 | N15: =IF(AND(ISNUMBER(E15),ISNUMBER(M15),OR(F15="W",F15="kWh")),M15/E15,"") | O15: https://electroimpulso.com.ar/catalogo/producto/growatt-spm-limitador-de-inyeccion-monofasico/
A16: LIM-03 | B16: Limitador | C16: Growatt TPM trifásico | D16: Growatt | F16: u | G16: SuriaEnergy | H16: 368535 | I16: Verificar | J16: Sin fecha | M16: =IF(K16<>"",K16,IF(H16="","",H16)) -> 368535 | N16: =IF(AND(ISNUMBER(E16),ISNUMBER(M16),OR(F16="W",F16="kWh")),M16/E16,"") | O16: https://shop.suriaenergy.com/40c760-Inversores%20On%20Grid
A17: BAT-01 | B17: Batería | C17: Deye SE-F5 5,12 kWh 51,2 V | D17: Deye | E17: 5.12 | F17: kWh | G17: Enertik | H17: 2752700 | I17: Incluido | J17: Sin fecha | M17: =IF(K17<>"",K17,IF(H17="","",H17)) -> 2752700 | N17: =IF(AND(ISNUMBER(E17),ISNUMBER(M17),OR(F17="W",F17="kWh")),M17/E17,"") -> 537636.72 | O17: https://enertik.com/ar/categoria/baterias/litio | P17: Mejor $/kWh relevado.
A18: BAT-02 | B18: Batería | C18: Dyness DL5.0C 5,12 kWh 48 V | D18: Dyness | E18: 5.12 | F18: kWh | G18: Mercado Libre | H18: 2983750 | I18: Incluido | J18: Actual al relevar | M18: =IF(K18<>"",K18,IF(H18="","",H18)) -> 2983750 | N18: =IF(AND(ISNUMBER(E18),ISNUMBER(M18),OR(F18="W",F18="kWh")),M18/E18,"") -> 582763.67 | O18: https://www.mercadolibre.com.ar/bateria-litio-solar-48v-dyness-dl50c-100ah-lifepo4-51kw/up/MLAU452853384 | P18: Permite cuotas.
A19: BAT-03 | B19: Batería | C19: Pylontech US5000 4,8 kWh 48 V | D19: Pylontech | E19: 4.8 | F19: kWh | G19: Enertik | H19: 4411900 | I19: Incluido | J19: Sin fecha | M19: =IF(K19<>"",K19,IF(H19="","",H19)) -> 4411900 | N19: =IF(AND(ISNUMBER(E19),ISNUMBER(M19),OR(F19="W",F19="kWh")),M19/E19,"") -> 919145.83 | O19: https://enertik.com/ar/marca/pylontech/ | P19: Premium. Enertik es distribuidor oficial.
A20: BAT-04 | B20: Batería | C20: Pylontech US5000 4,8 kWh 48 V | D20: Pylontech | E20: 4.8 | F20: kWh | G20: MCSoL | H20: 3670348.5 | I20: Verificar | J20: Sin stock al relevar | M20: =IF(K20<>"",K20,IF(H20="","",H20)) -> 3670348.5 | N20: =IF(AND(ISNUMBER(E20),ISNUMBER(M20),OR(F20="W",F20="kWh")),M20/E20,"") -> 764655.93 | O20: https://mcsol.com.ar/productos/bateria-pylontech-us5000-100ah-48v-litio-lifepo4/
A21: CAB-01 | B21: Cable | C21: Cable solar 6 mm² rojo/negro, rollo 30 m | D21: Varias | E21: 30 | F21: m | G21: Mercado Libre | H21: 115237 | I21: Incluido | J21: Actual al relevar | M21: =IF(K21<>"",K21,IF(H21="","",H21)) -> 115237 | N21: =IF(AND(ISNUMBER(E21),ISNUMBER(M21),OR(F21="W",F21="kWh")),M21/E21,"") | O21: https://listado.mercadolibre.com.ar/cable-solar-6mm | P21: Otro vendedor: $106.457.
A22: CAB-02 | B22: Cable | C22: Cable solar 6 mm², rollo 40 m | D22: Varias | E22: 40 | F22: m | G22: Mercado Libre | H22: 141250 | I22: Incluido | J22: Actual al relevar | M22: =IF(K22<>"",K22,IF(H22="","",H22)) -> 141250 | N22: =IF(AND(ISNUMBER(E22),ISNUMBER(M22),OR(F22="W",F22="kWh")),M22/E22,"") | O22: https://listado.mercadolibre.com.ar/cable-solar-6mm
A23: CON-01 | B23: Conector | C23: Conector MC4 (par macho/hembra) | D23: Genérico | F23: u | G23: Emakers | H23: 3731 | I23: Verificar | J23: Sin fecha | M23: =IF(K23<>"",K23,IF(H23="","",H23)) -> 3731 | N23: =IF(AND(ISNUMBER(E23),ISNUMBER(M23),OR(F23="W",F23="kWh")),M23/E23,"") | O23: https://www.emakers.com.ar/tienda/energia-solar-y-alternativas/accesorios-solar | P23: Verificar si el precio es por par o por unidad.
A24: CON-02 | B24: Conector | C24: MC4 en Y (1 a 3), par | D24: Genérico | F24: u | G24: Mercado Libre | H24: 35000 | I24: Incluido | J24: Actual al relevar | M24: =IF(K24<>"",K24,IF(H24="","",H24)) -> 35000 | N24: =IF(AND(ISNUMBER(E24),ISNUMBER(M24),OR(F24="W",F24="kWh")),M24/E24,"") | O24: https://listado.mercadolibre.com.ar/conectores-mc4-cable | P24: Solo si tenés strings en paralelo.
A25: PRO-01 | B25: Protección CC | C25: Portafusible + fusible gPV 1000 V CC 25 A | D25: Suntree | F25: u | G25: Hissuma materiales | J25: A cotizar | M25: =IF(K25<>"",K25,IF(H25="","",H25)) | N25: =IF(AND(ISNUMBER(E25),ISNUMBER(M25),OR(F25="W",F25="kWh")),M25/E25,"") | O25: https://www.hissuma-materiales.com.ar/productos/porta-fusible-con-fusible-cc-para-riel-din-25a-suntree/ | P25: Precio no publicado.
A26: PRO-02 | B26: Protección CC | C26: Seccionador CC 1000 V 2 o 4 polos | D26: Varias | F26: u | G26: A cotizar | J26: A cotizar | M26: =IF(K26<>"",K26,IF(H26="","",H26)) | N26: =IF(AND(ISNUMBER(E26),ISNUMBER(M26),OR(F26="W",F26="kWh")),M26/E26,"")
A27: PRO-03 | B27: Protección CC | C27: DPS CC tipo 2 1000 V | D27: Varias | F27: u | G27: A cotizar | J27: A cotizar | M27: =IF(K27<>"",K27,IF(H27="","",H27)) | N27: =IF(AND(ISNUMBER(E27),ISNUMBER(M27),OR(F27="W",F27="kWh")),M27/E27,"")
A28: PRO-04 | B28: Protección CA | C28: Térmica + disyuntor diferencial + DPS CA | D28: Schneider / ABB / Sica | F28: juego | G28: Casa de electricidad | J28: A cotizar | M28: =IF(K28<>"",K28,IF(H28="","",H28)) | N28: =IF(AND(ISNUMBER(E28),ISNUMBER(M28),OR(F28="W",F28="kWh")),M28/E28,"")
A29: EST-01 | B29: Estructura | C29: Estructura aluminio coplanar (por panel) | D29: Local | F29: panel | G29: A cotizar | J29: A cotizar | M29: =IF(K29<>"",K29,IF(H29="","",H29)) | N29: =IF(AND(ISNUMBER(E29),ISNUMBER(M29),OR(F29="W",F29="kWh")),M29/E29,"") | P29: Pedí precio con medidas del panel y tipo de techo.

Sheet Kits
A1: Kits de referencia (materiales a precio de lista, sin mano de obra ni margen)
A2: Cambiá el ID para usar otro producto de la hoja 'Productos', ajustá cantidades (azul) y completá lo amarillo.
A4: KIT A: Autoconsumo con inyección cero, ~2,2 kWp (cliente sin baterías)
A5: ID producto | B5: Descripción | C5: Cantidad | D5: Precio unitario (ARS) | E5: Subtotal (ARS) | F5: Nota
A6: PAN-01 | B6: =IFERROR(INDEX(Productos!$C:$C,MATCH(A6,Productos!$A:$A,0)),"ID no encontrado") -> Trina Vertex 550 W (TSM-550DE19) | C6: 4 | D6: =IFERROR(INDEX(Productos!$M:$M,MATCH(A6,Productos!$A:$A,0)),"") -> 224000 | E6: =IF(ISNUMBER(D6),C6*D6,0) -> 896000 | F6: 4 x 550 W = 2,2 kWp. Ajustar según el consumo de día.
A7: INV-02 | B7: =IFERROR(INDEX(Productos!$C:$C,MATCH(A7,Productos!$A:$A,0)),"ID no encontrado") -> Deye 3 kW on-grid | C7: 1 | D7: =IFERROR(INDEX(Productos!$M:$M,MATCH(A7,Productos!$A:$A,0)),"") -> 936889 | E7: =IF(ISNUMBER(D7),C7*D7,0) -> 936889 | F7: Deye 3 kW on-grid con limitación por CT.
A8: CAB-01 | B8: =IFERROR(INDEX(Productos!$C:$C,MATCH(A8,Productos!$A:$A,0)),"ID no encontrado") -> Cable solar 6 mm² rojo/negro, rollo 30 m | C8: 1 | D8: =IFERROR(INDEX(Productos!$M:$M,MATCH(A8,Productos!$A:$A,0)),"") -> 115237 | E8: =IF(ISNUMBER(D8),C8*D8,0) -> 115237 | F8: 1 rollo de 30 m. Ajustar según el recorrido.
A9: CON-01 | B9: =IFERROR(INDEX(Productos!$C:$C,MATCH(A9,Productos!$A:$A,0)),"ID no encontrado") -> Conector MC4 (par macho/hembra) | C9: 4 | D9: =IFERROR(INDEX(Productos!$M:$M,MATCH(A9,Productos!$A:$A,0)),"") -> 3731 | E9: =IF(ISNUMBER(D9),C9*D9,0) -> 14924
B10: Protecciones CC (fusibles, seccionador, DPS) | C10: 1 | E10: =IF(ISNUMBER(D10),C10*D10,0) -> 0 | F10: A cotizar
B11: Protecciones CA (térmica, diferencial, DPS) | C11: 1 | E11: =IF(ISNUMBER(D11),C11*D11,0) -> 0 | F11: A cotizar
B12: Estructura aluminio (por panel) | C12: 4 | E12: =IF(ISNUMBER(D12),C12*D12,0) -> 0 | F12: A cotizar
B13: Gabinete, cañería, cable CA, tierra, varios | C13: 1 | E13: =IF(ISNUMBER(D13),C13*D13,0) -> 0 | F13: A cotizar
D14: TOTAL materiales | E14: =SUM(E6:E13) -> 1963050
D15: Ítems sin precio | E15: =COUNTIF(D6:D13,"") -> 4 | F15: Si es mayor a 0, el total todavía no está completo.
A17: KIT B: Híbrido con baterías, ~3,3 kWp + 5 kWh (cliente con banco de baterías)
A18: ID producto | B18: Descripción | C18: Cantidad | D18: Precio unitario (ARS) | E18: Subtotal (ARS) | F18: Nota
A19: PAN-01 | B19: =IFERROR(INDEX(Productos!$C:$C,MATCH(A19,Productos!$A:$A,0)),"ID no encontrado") -> Trina Vertex 550 W (TSM-550DE19) | C19: 6 | D19: =IFERROR(INDEX(Productos!$M:$M,MATCH(A19,Productos!$A:$A,0)),"") -> 224000 | E19: =IF(ISNUMBER(D19),C19*D19,0) -> 1344000 | F19: 6 x 550 W = 3,3 kWp.
A20: INV-05 | B20: =IFERROR(INDEX(Productos!$C:$C,MATCH(A20,Productos!$A:$A,0)),"ID no encontrado") -> Deye SUN-5K-SG04LP1 5 kW 48 V | C20: 1 | D20: =IFERROR(INDEX(Productos!$M:$M,MATCH(A20,Productos!$A:$A,0)),"") -> 3916000 | E20: =IF(ISNUMBER(D20),C20*D20,0) -> 3916000 | F20: Deye híbrido 5 kW 48 V.
A21: BAT-01 | B21: =IFERROR(INDEX(Productos!$C:$C,MATCH(A21,Productos!$A:$A,0)),"ID no encontrado") -> Deye SE-F5 5,12 kWh 51,2 V | C21: 1 | D21: =IFERROR(INDEX(Productos!$M:$M,MATCH(A21,Productos!$A:$A,0)),"") -> 2752700 | E21: =IF(ISNUMBER(D21),C21*D21,0) -> 2752700 | F21: 5,12 kWh. Sumar módulos según las horas de respaldo.
A22: CAB-01 | B22: =IFERROR(INDEX(Productos!$C:$C,MATCH(A22,Productos!$A:$A,0)),"ID no encontrado") -> Cable solar 6 mm² rojo/negro, rollo 30 m | C22: 1 | D22: =IFERROR(INDEX(Productos!$M:$M,MATCH(A22,Productos!$A:$A,0)),"") -> 115237 | E22: =IF(ISNUMBER(D22),C22*D22,0) -> 115237
A23: CON-01 | B23: =IFERROR(INDEX(Productos!$C:$C,MATCH(A23,Productos!$A:$A,0)),"ID no encontrado") -> Conector MC4 (par macho/hembra) | C23: 4 | D23: =IFERROR(INDEX(Productos!$M:$M,MATCH(A23,Productos!$A:$A,0)),"") -> 3731 | E23: =IF(ISNUMBER(D23),C23*D23,0) -> 14924
B24: Protecciones CC + fusible/breaker de batería | C24: 1 | E24: =IF(ISNUMBER(D24),C24*D24,0) -> 0 | F24: A cotizar
B25: Protecciones CA + tablero de cargas críticas | C25: 1 | E25: =IF(ISNUMBER(D25),C25*D25,0) -> 0 | F25: A cotizar
B26: Estructura aluminio (por panel) | C26: 6 | E26: =IF(ISNUMBER(D26),C26*D26,0) -> 0 | F26: A cotizar
B27: Gabinete, cañería, cable CA, tierra, varios | C27: 1 | E27: =IF(ISNUMBER(D27),C27*D27,0) -> 0 | F27: A cotizar
D28: TOTAL materiales | E28: =SUM(E19:E27) -> 8142861
D29: Ítems sin precio | E29: =COUNTIF(D19:D27,"") -> 4 | F29: Si es mayor a 0, el total todavía no está completo.

Sheet Proveedores
A1: Proveedor | B1: Tipo | C1: Zona | D1: Qué vende | E1: Web | F1: Nota
A2: Enertik | B2: Tienda online / distribuidor | C2: Rosario (envíos a todo el país) | D2: Paneles Trina, baterías Deye y Pylontech (oficial), limitadores Growatt | E2: https://enertik.com/ar/tienda/ | F2: El más completo para comprar por unidad. Vende también en Mercado Libre.
A3: Mercado Libre | B3: Marketplace | C3: Todo el país | D3: De todo: paneles, inversores, baterías, cable, MC4 | E3: https://www.mercadolibre.com.ar | F3: Cuotas y envío rápido. Revisá la reputación del vendedor y la factura.
A4: SuriaEnergy | B4: Tienda online | C4: Verificar | D4: Inversores on-grid Deye, limitadores Growatt | E4: https://shop.suriaenergy.com/ | F4: Buenos precios de limitadores.
A5: Electroimpulso | B5: Tienda online | C5: Verificar | D5: Limitadores Growatt y accesorios | E5: https://electroimpulso.com.ar/
A6: Ingeniería Boggio | B6: Tienda online | C6: Verificar | D6: Inversores on-grid (SolaX y otros) | E6: https://www.ingenieriaboggio.com.ar/ | F6: Publica precios sin impuestos nacionales.
A7: JF Solar | B7: Tienda / distribuidor | C7: Verificar | D7: Paneles Amerisolar y JA Solar | E7: https://jfsolar.com.ar/ | F7: Precios publicados viejos: pedí lista actualizada.
A8: TexSolar (Solartex) | B8: Fabricante / distribuidor | C8: Roldán, Rosario | D8: Paneles Solartex bifaciales | E8: https://texsolar.com.ar/ | F8: Precio + IVA. Consultá el flete a AMBA.
A9: Hissuma materiales | B9: Mayorista | C9: General Rodríguez (Bs. As.) | D9: Growatt, Must, EPEver, protecciones Suntree | E9: https://www.hissuma-materiales.com.ar/ | F9: Cerca de AMBA. Ideal para protecciones CC. Preguntá si vende por unidad.
A10: Enerton | B10: Importador mayorista | C10: Verificar | D10: Paneles, inversores Deye, baterías Deye y Sunwoda | E10: https://www.enerton.com.ar/ | F10: Para cuando tengas volumen.
A11: ADN Solar | B11: Tienda online | C11: Verificar | D11: Paneles, inversores, baterías de litio, kits | E11: https://adnsolar.com.ar/ | F11: Precios en pesos online.
A12: FC Solar Energy | B12: Local comercial | C12: Gerli (Bs. As.) | D12: Kits, baterías Pylontech, inversores | E12: https://www.fcsolarenergy.com/ | F12: Local físico en AMBA.
A13: Todo Solar | B13: Tienda | C13: Verificar | D13: Paneles, inversores, baterías gel y litio | E13: https://www.todosolar.com.ar/
A14: MCSoL | B14: Tienda online | C14: Verificar | D14: Baterías Pylontech | E14: https://mcsol.com.ar/ | F14: Revisar stock.
A15: Casa de electricidad del barrio | B15: Comercio | C15: Tu zona | D15: Térmicas, diferenciales, DPS CA, cañería, cable CA | E15: — | F15: Pedí precio de gremio/instalador.
